Workbook
Name Slicer_Category: #N/A

Sheet DASHBOARD
AJ1: Months | AK1: Sum of Total_Amount
AJ2: Jan | AK2: 25799.15
AJ3: Feb | AK3: 16069.38
AJ4: Mar | AK4: 19899.38
AJ5: Apr | AK5: 27899.16
AJ6: May | AK6: 17039.35
AJ7: Jun | AK7: 19299.45
AJ8: Jul | AK8: 18479.4
AJ9: Aug | AK9: 15759.43
AJ10: Sep | AK10: 12989.51
AJ11: Oct | AK11: 20609.52
AJ12: Nov | AK12: 12309.44
AJ13: Dec | AK13: 23039.3
AJ14: Grand Total | AK14: 229192.47

Sheet Raw Data
A1: Transaction_ID | B1: Date | C1: Customer_ID | D1: Customer_Name | E1: Product_ID | F1: Product_Name | G1: Category | H1: Quantity | I1: Unit_Price | J1: Payment_Method | K1: Region | L1: Customer_Segment | M1: Customer_Since | N1: Total_Amount
A2: TRX0155 | B2: 45393 | C2: CUST023 | D2: Paul Baker | E2: P009 | F2: Monitor | G2: Electronics | H2: 3 | I2: 249.99 | J2: Cash | K2: Central | L2: Basic | M2: 44425 | N2: =I2*H2 -> 749.97
A3: TRX0023 | B3: 45396 | C3: CUST013 | D3: Joseph Jackson | E3: P009 | F3: Monitor | G3: Electronics | H3: 3 | I3: 249.99 | J3: Credit Card | K3: Central | L3: Premium | M3: 44575 | N3: =I3*H3 -> 749.97
A4: TRX0139 | B4: 45399 | C4: CUST021 | D4: Kevin Scott | E4: P005 | F4: Blender | G4: Appliances | H4: 3 | I4: 59.99 | J4: PayPal | K4: South | L4: Standard | M4: 45262 | N4: =I4*H4 -> 179.97
A5: TRX0043 | B5: 45400 | C5: CUST046 | D5: Kathleen Bennett | E5: P005 | F5: Blender | G5: Appliances | H5: 3 | I5: 59.99 | J5: Cash | K5: North | L5: Premium | M5: 45114 | N5: =I5*H5 -> 179.97
A6: TRX0212 | B6: 45400 | C6: CUST003 | D6: Michael Brown | E6: P008 | F6: Bookshelf | G6: Furniture | H6: 5 | I6: 149.99 | J6: Credit Card | K6: North | L6: Premium | M6: 45295 | N6: =I6*H6 -> 749.95
A7: TRX0092 | B7: 45403 | C7: CUST024 | D7: Dorothy Nelson | E7: P005 | F7: Blender | G7: Appliances | H7: 2 | I7: 59.99 | J7: Cash | K7: West | L7: Standard | M7: 44746 | N7: =I7*H7 -> 119.98
A8: TRX0193 | B8: 45403 | C8: CUST024 | D8: Dorothy Nelson | E8: P003 | F8: Headphones | G8: Electronics | H8: 5 | I8: 149.99 | J8: Credit Card | K8: Central | L8: Standard | M8: 44418 | N8: =I8*H8 -> 749.95
A9: TRX0240 | B9: 45403 | C9: CUST017 | D9: Charles Allen | E9: P005 | F9: Blender | G9: Appliances | H9: 3 | I9: 59.99 | J9: Debit Card | K9: South | L9: Basic | M9: 45007 | N9: =I9*H9 -> 179.97
A10: TRX0135 | B10: 45405 | C10: CUST009 | D10: Robert Thomas | E10: P001 | F10: Laptop | G10: Electronics | H10: 3 | I10: 899.99 | J10: PayPal | K10: East | L10: Standard | M10: 45299 | N10: =I10*H10 -> 2699.97
A11: TRX0185 | B11: 45408 | C11: CUST026 | D11: Karen Hill | E11: P005 | F11: Blender | G11: Appliances | H11: 3 | I11: 59.99 | J11: Cash | K11: West | L11: Premium | M11: 45207 | N11: =I11*H11 -> 179.97
A12: TRX0138 | B12: 45408 | C12: CUST022 | D12: Susan Green | E12: P008 | F12: Bookshelf | G12: Furniture | H12: 1 | I12: 149.99 | J12: Credit Card | K12: West | L12: Standard | M12: 45103 | N12: =I12*H12 -> 149.99
A13: TRX0209 | B13: 45408 | C13: CUST046 | D13: Kathleen Bennett | E13: P008 | F13: Bookshelf | G13: Furniture | H13: 5 | I13: 149.99 | J13: Debit Card | K13: North | L13: Basic | M13: 44830 | N13: =I13*H13 -> 749.95
... A251: TRX0064 | B251: 45758 | C251: CUST031 | D251: Steven Turner | E251: P010 | F251: Keyboard | G251: Electronics | H251: 3 | I251: 89.99 | J251: Debit Card | K251: North | L251: Premium | M251: 44878 | N251: =I251*H251 -> 269.97

Sheet Analysis
A1: 📅 Date & Time Functions
A2: Metric | B2: Value
A3: TODAY() | B3: =TODAY() -> 46173
A4: NOW() | B4: =NOW() -> 46173.634
A5: Days Span (DATEDIF) | B5: =DATEDIF(MIN('[1]Raw Data'!B2:B251),MAX('[1]Raw Data'!B2:B251),"D") -> 365
A6: End of This Month | B6: =EOMONTH(TODAY(),0) -> 46173
A7: Timestamp (NOW) | B7: =NOW() -> 46173.634
A9: 🔧 INPUT ASSUMPTIONS (Changing Cells — Blue = User Input)
A10: Parameter | B10: Value
A11: Avg Order Value (Base) | B11: =AVERAGE('Raw Data'!N2:N251) -> 916.76988
A12: Transaction Count (Base) | B12: 250
A14: 📊 SCENARIO COMPARISON TABLE
A15: Scenario | B15: Avg Order Value ($) | C15: Transactions Count | D15: Projected Revenue ($)
A16: 📌 Base Case | B16: =B11 -> 916.76988 | C16: =B12 -> 250 | D16: =B16*C16 -> 229192.47
A17: 🔺 Optimistic (+20%) | B17: =B11*1.2 -> 1100.1239 | C17: =B12*1.1 -> 275 | D17: =B17*C17 -> 302534.06
A18: 🔻 Pessimistic (-15%) | B18: =B11*0.85 -> 779.2544 | C18: =B12*0.9 -> 225 | D18: =B18*C18 -> 175332.24
A19: 💥 Best Case (+35%) | B19: =B11*1.35 -> 1237.6393 | C19: =B12*1.2 -> 300 | D19: =B19*C19 -> 371291.8
A20: ⚠️ Worst Case (-25%) | B20: =B11*0.75 -> 687.57741 | C20: =B12*0.8 -> 200 | D20: =B20*C20 -> 137515.48
A22: GOAL SEEK TABLE
A23: Element | B23: Cell Reference | C23: Value / Target
A24: 📥 Set Cell (Result) | B24: D35 | C24: =B25*C27 -> 229192.5
A25: 📥 By Changing Cell | B25: 916.77 | C25: =B25 -> 916.77
A26: 🎯 To Value (Target) | B26: Manual Entry | C26: 250000
A27: 📌 Transactions Count | B27: Fixed at 250 | C27: 250
A29: 📊 GOAL SEEK RESULT — What Avg Order Value achieves $250,000 revenue?
A30: Metric | B30: Original Value | C30: Goal Seek Result | D30: Change Required
A31: Avg Order Value | B31: =AVERAGE('Raw Data'!N2:N251) -> 916.76988 | C31: =C26/C27 -> 1000 | D31: =C31-B31 -> 83.23012
A32: Projected Revenue | B32: =AVERAGE('Raw Data'!N2:N251)*250 -> 229192.47 | C32: =C26 -> 250000 | D32: =C32-B32 -> 20807.53
A33: Transaction Count | B33: 250 | C33: 250 | D33: 0
A35: Most Frequently Purchased Products
A36: Product Name | B36: Total Qty Sold | C36: Transaction Count | D36: Revenue
A37: Laptop | B37: =SUMIF('Raw Data'!F:F,A37,'Raw Data'!H:H) -> 75 | C37: =COUNTIF('Raw Data'!F:F,A37) -> 24 | D37: =SUMIF('Raw Data'!F:F,A37,'Raw Data'!N:N) -> 67499.25
A38: Smartphone | B38: =SUMIF('Raw Data'!F:F,A38,'Raw Data'!H:H) -> 96 | C38: =COUNTIF('Raw Data'!F:F,A38) -> 31 | D38: =SUMIF('Raw Data'!F:F,A38,'Raw Data'!N:N) -> 67199.04
A39: Headphones | B39: =SUMIF('Raw Data'!F:F,A39,'Raw Data'!H:H) -> 47 | C39: =COUNTIF('Raw Data'!F:F,A39) -> 16 | D39: =SUMIF('Raw Data'!F:F,A39,'Raw Data'!N:N) -> 7049.53
A40: Coffee Maker | B40: =SUMIF('Raw Data'!F:F,A40,'Raw Data'!H:H) -> 39 | C40: =COUNTIF('Raw Data'!F:F,A40) -> 14 | D40: =SUMIF('Raw Data'!F:F,A40,'Raw Data'!N:N) -> 3119.61
A41: Blender | B41: =SUMIF('Raw Data'!F:F,A41,'Raw Data'!H:H) -> 87 | C41: =COUNTIF('Raw Data'!F:F,A41) -> 29 | D41: =SUMIF('Raw Data'!F:F,A41,'Raw Data'!N:N) -> 5219.13
A42: Office Chair | B42: =SUMIF('Raw Data'!F:F,A42,'Raw Data'!H:H) -> 52 | C42: =COUNTIF('Raw Data'!F:F,A42) -> 15 | D42: =SUMIF('Raw Data'!F:F,A42,'Raw Data'!N:N) -> 10399.48
A43: Desk | B43: =SUMIF('Raw Data'!F:F,A43,'Raw Data'!H:H) -> 78 | C43: =COUNTIF('Raw Data'!F:F,A43) -> 26 | D43: =SUMIF('Raw Data'!F:F,A43,'Raw Data'!N:N) -> 23399.22
A44: Bookshelf | B44: =SUMIF('Raw Data'!F:F,A44,'Raw Data'!H:H) -> 102 | C44: =COUNTIF('Raw Data'!F:F,A44) -> 35 | D44: =SUMIF('Raw Data'!F:F,A44,'Raw Data'!N:N) -> 15298.98
A45: Monitor | B45: =SUMIF('Raw Data'!F:F,A45,'Raw Data'!H:H) -> 88 | C45: =COUNTIF('Raw Data'!F:F,A45) -> 26 | D45: =SUMIF('Raw Data'!F:F,A45,'Raw Data'!N:N) -> 21999.12
A46: Keyboard | B46: =SUMIF('Raw Data'!F:F,A46,'Raw Data'!H:H) -> 89 | C46: =COUNTIF('Raw Data'!F:F,A46) -> 34 | D46: =SUMIF('Raw Data'!F:F,A46,'Raw Data'!N:N) -> 8009.11
A48: ★ Most Purchased Product: | B48: =INDEX(A37:A46,MATCH(MAX(B37:B46),B37:B46,0)) -> Bookshelf
A50: 🔄 Compare Lists – Premium vs Standard Customers
A51: Premium Customers | B51: Standard Customers | C51: Matched (Both Lists)
A52: Joseph Jackson | B52: Kevin Scott | C52: =IFERROR(IF(COUNTIF($B$52:$B$63,A52)>0,A52,""),"")
A53: Kathleen Bennett | B53: Dorothy Nelson | C53: =IFERROR(IF(COUNTIF($B$52:$B$63,A53)>0,A53,""),"")
A54: Michael Brown | B54: Robert Thomas | C54: =IFERROR(IF(COUNTIF($B$52:$B$63,A54)>0,A54,""),"")
A55: Karen Hill | B55: Susan Green | C55: =IFERROR(IF(COUNTIF($B$52:$B$63,A55)>0,A55,""),"")
A56: Peter Richardson | B56: Dennis Gray | C56: =IFERROR(IF(COUNTIF($B$52:$B$63,A56)>0,A56,""),"")
A57: Mark Carter | B57: George Adams | C57: =IFERROR(IF(COUNTIF($B$52:$B$63,A57)>0,A57,""),"") -> Mark Carter
A58: Virginia Sanders | B58: Mark Carter | C58: =IFERROR(IF(COUNTIF($B$52:$B$63,A58)>0,A58,""),"")
A59: Linda Martin | B59: Patricia Moore | C59: =IFERROR(IF(COUNTIF($B$52:$B$63,A59)>0,A59,""),"")
A60: Patricia Moore | B60: Cynthia Price | C60: =IFERROR(IF(COUNTIF($B$52:$B$63,A60)>0,A60,""),"") -> Patricia Moore
A61: Emma Wilson | B61: Nancy Collins | C61: =IFERROR(IF(COUNTIF($B$52:$B$63,A61)>0,A61,""),"")
A62: Kevin Scott | B62: Helen Roberts | C62: =IFERROR(IF(COUNTIF($B$52:$B$63,A62)>0,A62,""),"") -> Kevin Scott
A63: Steven Turner | B63: Edward Mitchell | C63: =IFERROR(IF(COUNTIF($B$52:$B$63,A63)>0,A63,""),"")
A66: 📈 Linear Regression – Quantity vs Revenue
A67: Metric | B67: Value | C67: Formula Used | D67: Interpretation
A68: SLOPE (b1) | B68: =SLOPE('Raw Data'!#REF!,'Raw Data'!H2:H251) -> #REF! | C68: SLOPE(y,x) | D68: Revenue per additional unit
A69: INTERCEPT (b0) | B69: =INTERCEPT('Raw Data'!#REF!,'Raw Data'!H2:H251) -> #REF! | C69: INTERCEPT(y,x) | D69: Base revenue when qty=0
A70: R² (Correlation²) | B70: =RSQ('Raw Data'!#REF!,'Raw Data'!H2:H251) -> #REF! | C70: RSQ(y,x) | D70: Model fit (1=perfect)
A71: CORREL | B71: =CORREL('Raw Data'!#REF!,'Raw Data'!H2:H251) -> #REF! | C71: CORREL(y,x) | D71: Pearson correlation
A72: Predicted Rev @ Qty=3 | B72: =B68+B68*3 -> #REF! | C72: b0 + b1*x | D72: Forecast for 3 units
A74: 👑 High-Value Customer Analysis (GroupBy)
A75: Customer_Name | B75: Customer_ID | C75: Total Revenue | D75: Tx Count | E75: Avg Transaction | F75: Segment | G75: Abbreviation
A76: Mark Carter | B76: CUST025 | C76: =SUMIF('Raw Data'!D:D,A76,'Raw Data'!N:N) -> 15659.65 | D76: =COUNTIF('Raw Data'!D:D,A76) -> 12 | E76: =IFERROR(C76/D76,0) -> 1304.9708 | F76: Standard | G76: =UPPER(LEFT(A76,1))&"."&UPPER(MID(A76,FIND(" ",A76)+1,1))&"." -> M.C.
A77: Edward Mitchell | B77: CUST029 | C77: =SUMIF('Raw Data'!D:D,A77,'Raw Data'!N:N) -> 11919.77 | D77: =COUNTIF('Raw Data'!D:D,A77) -> 6 | E77: =IFERROR(C77/D77,0) -> 1986.6283 | F77: Premium | G77: =UPPER(LEFT(A77,1))&"."&UPPER(MID(A77,FIND(" ",A77)+1,1))&"." -> E.M.
A78: Karen Hill | B78: CUST026 | C78: =SUMIF('Raw Data'!D:D,A78,'Raw Data'!N:N) -> 8009.77 | D78: =COUNTIF('Raw Data'!D:D,A78) -> 8 | E78: =IFERROR(C78/D78,0) -> 1001.2212 | F78: Premium | G78: =UPPER(LEFT(A78,1))&"."&UPPER(MID(A78,FIND(" ",A78)+1,1))&"." -> K.H.
A79: Barbara Young | B79: CUST018 | C79: =SUMIF('Raw Data'!D:D,A79,'Raw Data'!N:N) -> 10649.8 | D79: =COUNTIF('Raw Data'!D:D,A79) -> 5 | E79: =IFERROR(C79/D79,0) -> 2129.96 | F79: Standard | G79: =UPPER(LEFT(A79,1))&"."&UPPER(MID(A79,FIND(" ",A79)+1,1))&"." -> B.Y.
A80: Joseph Jackson | B80: CUST013 | C80: =SUMIF('Raw Data'!D:D,A80,'Raw Data'!N:N) -> 6949.84 | D80: =COUNTIF('Raw Data'!D:D,A80) -> 5 | E80: =IFERROR(C80/D80,0) -> 1389.968 | F80: Standard | G80: =UPPER(LEFT(A80,1))&"."&UPPER(MID(A80,FIND(" ",A80)+1,1))&"." -> J.J.
A81: Paul Baker | B81: CUST023 | C81: =SUMIF('Raw Data'!D:D,A81,'Raw Data'!N:N) -> 8309.74 | D81: =COUNTIF('Raw Data'!D:D,A81) -> 8 | E81: =IFERROR(C81/D81,0) -> 1038.7175 | F81: Standard | G81: =UPPER(LEFT(A81,1))&"."&UPPER(MID(A81,FIND(" ",A81)+1,1))&"." -> P.B.
A82: Betty Campbell | B82: CUST028 | C82: =SUMIF('Raw Data'!D:D,A82,'Raw Data'!N:N) -> 5649.84 | D82: =COUNTIF('Raw Data'!D:D,A82) -> 5 | E82: =IFERROR(C82/D82,0) -> 1129.968 | F82: Premium | G82: =UPPER(LEFT(A82,1))&"."&UPPER(MID(A82,FIND(" ",A82)+1,1))&"." -> B.C.
A83: Helen Roberts | B83: CUST030 | C83: =SUMIF('Raw Data'!D:D,A83,'Raw Data'!N:N) -> 6459.79 | D83: =COUNTIF('Raw Data'!D:D,A83) -> 7 | E83: =IFERROR(C83/D83,0) -> 922.82714 | F83: Standard | G83: =UPPER(LEFT(A83,1))&"."&UPPER(MID(A83,FIND(" ",A83)+1,1))&"." -> H.R.
A84: Daniel King | B84: CUST019 | C84: =SUMIF('Raw Data'!D:D,A84,'Raw Data'!N:N) -> 7309.8 | D84: =COUNTIF('Raw Data'!D:D,A84) -> 7 | E84: =IFERROR(C84/D84,0) -> 1044.2571 | F84: Standard | G84: =UPPER(LEFT(A84,1))&"."&UPPER(MID(A84,FIND(" ",A84)+1,1))&"." -> D.K.
A85: Lawrence Reed | B85: CUST039 | C85: =SUMIF('Raw Data'!D:D,A85,'Raw Data'!N:N) -> 6989.77 | D85: =COUNTIF('Raw Data'!D:D,A85) -> 8 | E85: =IFERROR(C85/D85,0) -> 873.72125 | F85: Premium | G85: =UPPER(LEFT(A85,1))&"."&UPPER(MID(A85,FIND(" ",A85)+1,1))&"." -> L.R.
A86: Peter Richardson | B86: CUST041 | C86: =SUMIF('Raw Data'!D:D,A86,'Raw Data'!N:N) -> 5949.85 | D86: =COUNTIF('Raw Data'!D:D,A86) -> 5 | E86: =IFERROR(C86/D86,0) -> 1189.97 | F86: Basic | G86: =UPPER(LEFT(A86,1))&"."&UPPER(MID(A86,FIND(" ",A86)+1,1))&"." -> P.R.
A87: Harry Morgan | B87: CUST035 | C87: =SUMIF('Raw Data'!D:D,A87,'Raw Data'!N:N) -> 5519.89 | D87: =COUNTIF('Raw Data'!D:D,A87) -> 4 | E87: =IFERROR(C87/D87,0) -> 1379.9725 | F87: Premium | G87: =UPPER(LEFT(A87,1))&"."&UPPER(MID(A87,FIND(" ",A87)+1,1))&"." -> H.M.
... A90: Patricia Moore | B90: CUST012 | C90: =SUMIF('Raw Data'!D:D,A90,'Raw Data'!N:N) -> 9799.73 | D90: =COUNTIF('Raw Data'!D:D,A90) -> 8 | E90: =IFERROR(C90/D90,0) -> 1224.9662 | F90: Premium | G90: =UPPER(LEFT(A90,1))&"."&UPPER(MID(A90,FIND(" ",A90)+1,1))&"." -> P.M.
A92: Regional Sales Summary
A93: Region | B93: Revenue | C93: Transactions | D93: Avg Order
A94: North | B94: =SUMIF('Raw Data'!K:K,A94,'Raw Data'!N:N) -> 50808.31 | C94: =COUNTIF('Raw Data'!K:K,A94) -> 59 | D94: =IFERROR(B94/C94,0) -> 861.1578
A95: South | B95: =SUMIF('Raw Data'!K:K,A95,'Raw Data'!N:N) -> 36398.75 | C95: =COUNTIF('Raw Data'!K:K,A95) -> 42 | D95: =IFERROR(B95/C95,0) -> 866.6369
A96: East | B96: =SUMIF('Raw Data'!K:K,A96,'Raw Data'!N:N) -> 59288.39 | C96: =COUNTIF('Raw Data'!K:K,A96) -> 48 | D96: =IFERROR(B96/C96,0) -> 1235.1748
A97: West | B97: =SUMIF('Raw Data'!K:K,A97,'Raw Data'!N:N) -> 41408.68 | C97: =COUNTIF('Raw Data'!K:K,A97) -> 47 | D97: =IFERROR(B97/C97,0) -> 881.03574
A98: Central | B98: =SUMIF('Raw Data'!K:K,A98,'Raw Data'!N:N) -> 41288.34 | C98: =COUNTIF('Raw Data'!K:K,A98) -> 54 | D98: =IFERROR(B98/C98,0) -> 764.59889

Sheet Visualization
A1: Region | B1: Revenue
A2: Central | B2: 1999.71
A3: East | B3: 2239.67
A4: North | B4: 1119.84
A5: South | B5: 1099.83
A6: West | B6: 1879.69
A7: Grand Total | B7: 8338.74
A20: Product | B20: Revenue
A21: Blender | B21: 5219.13
A22: Bookshelf | B22: 15298.98
A23: Coffee Maker | B23: 3119.61
A24: Desk | B24: 23399.22
A25: Headphones | B25: 7049.53
A26: Keyboard | B26: 8009.11
A27: Laptop | B27: 67499.25
A28: Monitor | B28: 21999.12
A29: Office Chair | B29: 10399.48
A30: Smartphone | B30: 67199.04
A31: Grand Total | B31: 229192.47
A38: Payment method | B38: Count
A39: Cash | B39: 76
A40: Credit Card | B40: 68
A41: Debit Card | B41: 54
A42: PayPal | B42: 52
A43: Grand Total | B43: 250
A58: Row Labels | B58: Revenue
A59: Appliances | B59: 8338.74
A60: Electronics | B60: 171756.05
A61: Furniture | B61: 49097.68
A62: Grand Total | B62: 229192.47
A76: Months | B76: Sum of Total_Amount
A77: Jan | B77: 25799.15
A78: Feb | B78: 16069.38
A79: Mar | B79: 19899.38
A80: Apr | B80: 27899.16
A81: May | B81: 17039.35
A82: Jun | B82: 19299.45
A83: Jul | B83: 18479.4
A84: Aug | B84: 15759.43
A85: Sep | B85: 12989.51
A86: Oct | B86: 20609.52
A87: Nov | B87: 12309.44
A88: Dec | B88: 23039.3
A89: Grand Total | B89: 229192.47
